sdgne/__init__.py
sdgne/datagenerator/__init__.py
sdgne/datagenerator/autoencoder.py
sdgne/datagenerator/smote.py
sdgne/demodata/__init__.py
sdgne/demodata/data.csv
sdgne/demodata/demodataset.py
sdgne/evaluator/__init__.py
sdgne/evaluator/evaluator.py
sdgne/models/__init__.py
sdgne/models/balanced_autoencoder.h5
sdgne/models/heavy_decoder_autoencoder.h5
sdgne/models/single_encoder_autoencoder.h5
sdgne-4.0.0.dist-info/LICENSE
sdgne-4.0.0.dist-info/METADATA
sdgne-4.0.0.dist-info/WHEEL
sdgne-4.0.0.dist-info/top_level.txt
sdgne-4.0.0.dist-info/RECORD
