Metadata-Version: 2.1
Name: sdgne
Version: 4.0.0
Summary: Synthetic Data Generation and Evaluation
Home-page: https://github.com/SartajBhuvaji
Author: Sartaj Bhuvaji
Author-email: s.bhuvaj@gmail.com
Keywords: python,synthetic data,autoencoders,smote
Classifier: Development Status :: 5 - Production/Stable
Classifier: Intended Audience :: Developers
Classifier: Programming Language :: Python :: 3.7
Classifier: Operating System :: Unix
Classifier: Operating System :: MacOS :: MacOS X
Classifier: Operating System :: Microsoft :: Windows
License-File: LICENSE
